shopee_wrapper/__init__.py
shopee_wrapper/base.py
shopee_wrapper/product.py
shopee_wrapper/review.py
shopee_wrapper/shop.py
shopee_wrapper/type.py
wrapper/__init__.py
wrapper/base.py
wrapper/product.py
wrapper/review.py
wrapper/shop.py
wrapper/type.py
shopee_wrapper-0.5.dist-info/METADATA
shopee_wrapper-0.5.dist-info/WHEEL
shopee_wrapper-0.5.dist-info/top_level.txt
shopee_wrapper-0.5.dist-info/RECORD
